Metadata-Version: 2.4
Name: ordeq_matplotlib
Version: 1.0.0
Author: Niels Neerhoff, Simon Brugman
Maintainer: Niels Neerhoff, Simon Brugman
License-Expression: MIT
Requires-Python: >=3.10
License-File: LICENSE
Requires-Dist: ordeq>=0.2.1
Requires-Dist: matplotlib
Dynamic: license-file
